cdk_iam_floyd/__init__.py
cdk_iam_floyd/py.typed
cdk_iam_floyd/_jsii/__init__.py
cdk_iam_floyd/_jsii/cdk-iam-floyd@0.480.2.jsii.tgz
cdk_iam_floyd-0.480.2.dist-info/LICENSE
cdk_iam_floyd-0.480.2.dist-info/METADATA
cdk_iam_floyd-0.480.2.dist-info/WHEEL
cdk_iam_floyd-0.480.2.dist-info/top_level.txt
cdk_iam_floyd-0.480.2.dist-info/RECORD
